bliz/__init__.py
bliz/logger.py
bliz/builder/__init__.py
bliz/builder/base_model.py
bliz/builder/builder.py
bliz/builder/constants.py
bliz/builder/data_prep.py
bliz/builder/save_load_model.py
bliz/builder/utils.py
bliz/evaluation/__init__.py
bliz/evaluation/constants.py
bliz/evaluation/experiment.py
bliz/evaluation/metrics.py
bliz/evaluation/monte_carlo.py
bliz/evaluation/norms.py
bliz/evaluation/simulation_data.py
bliz/evaluation/utils.py
bliz/evaluation/plotting/__init__.py
bliz/evaluation/plotting/hist.py
bliz/evaluation/plotting/result_data.py
bliz-0.1.3.dist-info/LICENSE
bliz-0.1.3.dist-info/METADATA
bliz-0.1.3.dist-info/WHEEL
bliz-0.1.3.dist-info/top_level.txt
bliz-0.1.3.dist-info/RECORD
